triplet_tools/__init__.py
triplet_tools/losses/__init__.py
triplet_tools/losses/shared_functions.py
triplet_tools/losses/triplet_batch_hard_loss.py
triplet_tools/losses/triplet_batch_priming_loss.py
triplet_tools/losses/triplet_batch_semihard_loss.py
triplet_tools-0.2.3.dist-info/LICENSE
triplet_tools-0.2.3.dist-info/METADATA
triplet_tools-0.2.3.dist-info/WHEEL
triplet_tools-0.2.3.dist-info/top_level.txt
triplet_tools-0.2.3.dist-info/RECORD
